brood/__init__.py
brood/actions.py
brood/api.py
brood/cli.py
brood/data.py
brood/db.py
brood/exceptions.py
brood/middleware.py
brood/models.py
brood/settings.py
brood/subscriptions.py
brood/version.py
brood/resources/__init__.py
brood/resources/actions.py
brood/resources/api.py
brood/resources/cli.py
brood/resources/data.py
brood/resources/exceptions.py
brood/resources/models.py
brood/resources/version.py
bugout_brood-0.3.1.dist-info/LICENSE
bugout_brood-0.3.1.dist-info/METADATA
bugout_brood-0.3.1.dist-info/WHEEL
bugout_brood-0.3.1.dist-info/entry_points.txt
bugout_brood-0.3.1.dist-info/top_level.txt
bugout_brood-0.3.1.dist-info/RECORD
