Metadata-Version: 2.1
Name: bugout-brood
Version: 0.3.1
Summary: Brood: Bugout authentication
Home-page: https://github.com/simiotics/brood
Author: Bugout.dev
Author-email: engineering@bugout.dev
License: UNKNOWN
Platform: UNKNOWN
Classifier: Development Status :: 3 - Alpha
Classifier: Intended Audience :: Developers
Classifier: Natural Language :: English
Classifier: Programming Language :: Python
Classifier: License :: OSI Approved :: Apache Software License
Classifier: Topic :: Software Development :: Libraries
Requires-Dist: argon2-cffi
Requires-Dist: boto3 (>=1.20.2)
Requires-Dist: fastapi (>=0.70.0)
Requires-Dist: passlib
Requires-Dist: psycopg2-binary
Requires-Dist: pydantic
Requires-Dist: python-multipart
Requires-Dist: sendgrid
Requires-Dist: sqlalchemy (>=1.4.26)
Requires-Dist: stripe (>=2.61.0)
Requires-Dist: uvicorn (>=0.15.0)
Requires-Dist: web3login[fastapi] (>=0.0.3)
Provides-Extra: dev
Requires-Dist: alembic (>=1.7.4) ; extra == 'dev'
Requires-Dist: black ; extra == 'dev'
Requires-Dist: isort ; extra == 'dev'
Requires-Dist: mypy ; extra == 'dev'
Provides-Extra: distribute
Requires-Dist: setuptools ; extra == 'distribute'
Requires-Dist: twine ; extra == 'distribute'
Requires-Dist: wheel ; extra == 'distribute'
